ptsecurixt/__init__.py
ptsecurixt/_version.py
ptsecurixt/ptsecurixt.py
ptsecurixt-1.0.4.dist-info/LICENSE
ptsecurixt-1.0.4.dist-info/METADATA
ptsecurixt-1.0.4.dist-info/WHEEL
ptsecurixt-1.0.4.dist-info/entry_points.txt
ptsecurixt-1.0.4.dist-info/top_level.txt
ptsecurixt-1.0.4.dist-info/RECORD
